[
    {
        "number": "1",
        "name": "Limonero 4.5%, from Tiny Rebel",
        "colour": "FEFA96"
    },
    {
        "number": "2",
        "name": "Hebden's Wheat 4.5%, from Little Valley",
        "colour": "FEFA96"
    },
    {
        "number": "3",
        "name": "Cascade Blonde 4.1%, from Prospect",
        "colour": "FEFA96"
    },
    {
        "number": "4",
        "name": "Blonde Vixen 3.8%, from Wily Fox",
        "colour": "FEFA96"
    },
    {
        "number": "5",
        "name": "Glacier 3.6%, from Beartown",
        "colour": "FEFA96"
    },
    {
        "number": "6",
        "name": "Busmans Golden 4.2%, from 4Ts",
        "colour": "F7D05A"
    },
    {
        "number": "7",
        "name": "Brother Rabbit 4%, from Thornbridge",
        "colour": "F7D05A"
    },
    {
        "number": "8",
        "name": "XPA 4.5%, from Tatton",
        "colour": "FEFA96"
    },
    {
        "number": "9",
        "name": "Otter's Tears 6%, from Thornbridge",
        "colour": "FEFA96"
    },
    {
        "number": "10",
        "name": "Belgian Blanche 4.7%, from 7 Brothers",
        "colour": "FEFA96"
    },
    {
        "number": "11",
        "name": "Green Hop Beer 4.1%, from Dunham Massey",
        "colour": "E7AC4F"
    },
    {
        "number": "12",
        "name": "UXB 4.4%, from Storm",
        "colour": "FEFA96"
    },
    {
        "number": "13",
        "name": "Lit 4.5%, from Beartown",
        "colour": "FEFA96"
    },
    {
        "number": "14",
        "name": "Black Ice 4.1%, from Titanic",
        "colour": "16120D"
    },
    {
        "number": "15",
        "name": "East India Pale Ale 6%, from Dunham Massey",
        "colour": "E5A74F"
    },
    {
        "number": "16",
        "name": "Raindance Grapefruit IPA 4.5%, from Mobberley Brewery",
        "colour": "FEFA96"
    },
    {
        "number": "17",
        "name": "Shameless 5.9%, from Red Willow",
        "colour": "E5A74F"
    },
    {
        "number": "18",
        "name": "Clipaty Hop 4.3%, from CoachHouse",
        "colour": "E5A74F"
    },
    {
        "number": "19",
        "name": "Warrior IPA 4%, from Wily Fox",
        "colour": "E5A74F"
    },
    {
        "number": "20",
        "name": "AM:PM 4.5%, Thornbridge",
        "colour": "E5A74F"
    },
    {
        "number": "21",
        "name": "The Pokies 3.6%, from Blackjack",
        "colour": "E5A74F"
    },
    {
        "number": "22",
        "name": "MCR 4.4%, from First Chop",
        "colour": "A65231"
    },
    {
        "number": "23",
        "name": "Best Bitter 3.7%, from Beartown",
        "colour": "A65231"
    },
    {
        "number": "24",
        "name": "Pioneer 4%, from Prospect",
        "colour": "A65231"
    },
    {
        "number": "25",
        "name": "Busmans Cherry Mild 3.8%, 4Ts",
        "colour": "A65231"
    },
    {
        "number": "26",
        "name": "1924 4%, from Mobberley",
        "colour": "A65231"
    },
    {
        "number": "27",
        "name": "First Class 3.8%, from Titanic",
        "colour": "A65231"
    },
    {
        "number": "28",
        "name": "Dick Turpin 4.2%, from CoachHouse",
        "colour": "A65231"
    },
    {
        "number": "29",
        "name": "Silk of Amnesia 4.7%, from Storm",
        "colour": "A65231"
    },
    {
        "number": "30",
        "name": "Ottowa 4.2%, from Hydes",
        "colour": "A65231"
    },
    {
        "number": "31",
        "name": "Salford Red 4.6%, from First Chop",
        "colour": "A65231"
    },
    {
        "number": "32",
        "name": "Innkepers Special Reserve 4.5%, from CoachHouse",
        "colour": "A65231"
    },
    {
        "number": "33",
        "name": "Malted Milk 4.6%, Tatton",
        "colour": "16120D"
    },
    {
        "number": "34",
        "name": "Faithless 121 Blackberry Stout 5.2%, from Red Willow",
        "colour": "16120D"
    },
    {
        "number": "35",
        "name": "Crème Beerle 4.8%, from Beartown",
        "colour": "16120D"
    },
    {
        "number": "36",
        "name": "Dark Vale 4.5%, from Little Valley",
        "colour": "16120D"
    },
    {
        "number": "37",
        "name": "Bridgewater Blonde 4.0%, from Lymm Brewing Co",
        "colour": "FDF583"
    },
    {
        "number": "38",
        "name": "Who Gose There Raspberry Rhubarb Ginger 4.5%, from Stubborn Mule",
        "colour": "FDF583"
    },
    {
        "number": "39",
        "name": "Mandarin Candidate 3.4%, from Stubborn Mule",
        "colour": "FDF583"
    },
    {
        "number": "40",
        "name": "Cerveceria Malteria Quilmes 4.9% Lager, from The Wine Kitchen",
        "colour": "F8DA63"
    }
]
